sji_load_tables/__init__.py
sji_load_tables/interp.py
sji_load_tables/joists.py
sji_load_tables/data/__init__.py
sji_load_tables/data/joist_data.json
sji_load_tables-0.0.1.dist-info/LICENSE
sji_load_tables-0.0.1.dist-info/METADATA
sji_load_tables-0.0.1.dist-info/WHEEL
sji_load_tables-0.0.1.dist-info/top_level.txt
sji_load_tables-0.0.1.dist-info/RECORD
