Metadata-Version: 2.1
Name: sji-load-tables
Version: 0.0.1
Summary: A package for looking up values from the Steel Joist Institute (SJI) load tables.
Home-page: https://github.com/denavit/sji_load_tables
Author: Mark Denavit
Author-email: mdenavit@utk.edu
License: MIT
Requires-Python: >=3.7
License-File: LICENSE
